pyflagser-0.4.7.dist-info/WHEEL
pyflagser-0.4.7.dist-info/LICENSE
pyflagser-0.4.7.dist-info/top_level.txt
pyflagser-0.4.7.dist-info/RECORD
pyflagser-0.4.7.dist-info/METADATA
pyflagser/_utils.py
pyflagser/flagser_count.py
pyflagser/__init__.py
pyflagser/flagio.py
pyflagser/flagser.py
pyflagser/_version.py
pyflagser/modules/flagser_pybind.cpython-38-x86_64-linux-gnu.so
pyflagser/modules/flagser_count_pybind.cpython-38-x86_64-linux-gnu.so
pyflagser/modules/flagser_coeff_pybind.cpython-38-x86_64-linux-gnu.so
pyflagser/tests/__main__.py
pyflagser/tests/conftest.py
pyflagser/tests/test_flagser_count.py
pyflagser/tests/__init__.py
pyflagser/tests/test_flagser.py
pyflagser/tests/test_flagio.py
