Metadata-Version: 2.1
Name: pyflagser
Version: 0.4.7
Summary: Python bindings for the flagser C++ library.
Home-page: https://github.com/giotto-ai/pyflagser
Download-URL: https://github.com/giotto-ai/pyflagser/tarball/v0.4.7
Maintainer: Guillaume Tauzin, Umberto Lupo
Maintainer-email: maintainers@giotto.ai
License: GNU AGPLv3
Keywords: topological data analysis,persistent homology,directed flags complex,persistence diagrams
Classifier: Intended Audience :: Science/Research
Classifier: Intended Audience :: Developers
Classifier: License :: OSI Approved
Classifier: Programming Language :: C++
Classifier: Programming Language :: Python
Classifier: Topic :: Software Development
Classifier: Topic :: Scientific/Engineering
Classifier: Operating System :: Microsoft :: Windows
Classifier: Operating System :: POSIX
Classifier: Operating System :: Unix
Classifier: Operating System :: MacOS
Classifier: Programming Language :: Python :: 3.7
Classifier: Programming Language :: Python :: 3.8
Classifier: Programming Language :: Python :: 3.9
Classifier: Programming Language :: Python :: 3.10
Classifier: Programming Language :: Python :: 3.11
Classifier: Programming Language :: Python :: 3.12
License-File: LICENSE
Requires-Dist: numpy >=1.17.0
Requires-Dist: scipy >=0.17.0
Provides-Extra: doc
Requires-Dist: sphinx ; extra == 'doc'
Requires-Dist: sphinx-gallery ; extra == 'doc'
Requires-Dist: sphinx-issues ; extra == 'doc'
Requires-Dist: sphinx-rtd-theme ; extra == 'doc'
Requires-Dist: numpydoc ; extra == 'doc'
Provides-Extra: tests
Requires-Dist: pytest ; extra == 'tests'
Requires-Dist: pytest-timeout ; extra == 'tests'
Requires-Dist: pytest-cov ; extra == 'tests'
Requires-Dist: pytest-azurepipelines ; extra == 'tests'
Requires-Dist: pytest-benchmark ; extra == 'tests'
Requires-Dist: flake8 ; extra == 'tests'
